[
  {
    "id": 7,
    "name": "力自慢Ⅰ",
    "kana": "ちからじまんいち",
    "text": "鍔迫り合い、または相殺が成功した時、一定時間、基礎攻撃力+10",
    "max": 1,
    "lv": {
      "1": "鍔迫り合い、または相殺が成功した時、一定時間、基礎攻撃力+10"
    }
  },
  {
    "id": 8,
    "name": "力自慢Ⅱ",
    "kana": "ちからじまんに",
    "text": "鍔迫り合い、または相殺が成功した時、一定時間、基礎攻撃力+25",
    "max": 1,
    "lv": {
      "1": "鍔迫り合い、または相殺が成功した時、一定時間、基礎攻撃力+25"
    }
  },
  {
    "id": 84,
    "name": "灼熱化Ⅰ",
    "kana": "しゃくねつかいち",
    "text": "攻撃を当てた時、確率で追加の火属性ダメージを与える",
    "max": 1,
    "lv": {
      "1": "攻撃を当てた時、確率で追加の火属性ダメージを与える"
    }
  },
  {
    "id": 85,
    "name": "灼熱化Ⅱ",
    "kana": "しゃくねつかに",
    "text": "追加で与える火属性ダメージが上昇する",
    "max": 1,
    "lv": {
      "1": "追加で与える火属性ダメージが上昇する"
    }
  },
  {
    "id": 86,
    "name": "連撃強化Ⅰ",
    "kana": "れんげききょうかいち",
    "text": "「連撃」スキルの効果発動時、有効時間を1秒延長し、基礎攻撃力+3",
    "max": 1,
    "lv": {
      "1": "「連撃」スキルの効果発動時、有効時間を1秒延長し、基礎攻撃力+3"
    }
  },
  {
    "id": 87,
    "name": "連撃強化Ⅱ",
    "kana": "れんげききょうかに",
    "text": "「連撃」スキルの効果発動時、有効時間を2秒延長し、基礎攻撃力+10",
    "max": 1,
    "lv": {
      "1": "「連撃」スキルの効果発動時、有効時間を2秒延長し、基礎攻撃力+10"
    }
  },
  {
    "id": 92,
    "name": "破壊衝動Ⅰ",
    "kana": "はかいしょうどういち",
    "text": "大型モンスターの傷口を破壊した時、体力が少し回復する",
    "max": 1,
    "lv": {
      "1": "大型モンスターの傷口を破壊した時、体力が少し回復する"
    }
  },
  {
    "id": 93,
    "name": "破壊衝動Ⅱ",
    "kana": "はかいしょうどうに",
    "text": "大型モンスターの傷口を破壊した時、体力が回復する",
    "max": 1,
    "lv": {
      "1": "大型モンスターの傷口を破壊した時、体力が回復する"
    }
  },
  {
    "id": 102,
    "name": "守護のヴェールⅠ",
    "kana": "しゅごのゔぇーる",
    "text": "特殊装具を使用した時、一定時間防御力と耐性値が上昇する",
    "max": 1,
    "lv": {
      "1": "特殊装具を使用した時、一定時間防御力と耐性値が上昇する"
    }
  },
  {
    "id": 103,
    "name": "守護のヴェールⅡ",
    "kana": "しゅごのゔぇーる",
    "text": "特殊装具を使用した時、一定時間防御力と耐性値が大きく上昇する",
    "max": 1,
    "lv": {
      "1": "特殊装具を使用した時、一定時間防御力と耐性値が大きく上昇する"
    }
  },
  {
    "id": 107,
    "name": "雷々響鳴Ⅰ",
    "kana": "らいらいきょうめい",
    "text": "「力の解放」のスキル発動時間を少し延長する",
    "max": 1,
    "lv": {
      "1": "「力の解放」のスキル発動時間を少し延長する"
    }
  },
  {
    "id": 108,
    "name": "雷々響鳴Ⅱ",
    "kana": "らいらいきょうめい",
    "text": "「力の解放」のスキル発動時間を延長する",
    "max": 1,
    "lv": {
      "1": "「力の解放」のスキル発動時間を延長する"
    }
  },
  {
    "id": 118,
    "name": "無尽蔵Ⅰ",
    "kana": "むじんぞう",
    "text": "追加のスタミナゲージを得る",
    "max": 1,
    "lv": {
      "1": "追加のスタミナゲージを得る"
    }
  },
  {
    "id": 119,
    "name": "無尽蔵Ⅱ",
    "kana": "むじんぞう",
    "text": "長い追加のスタミナゲージを得る",
    "max": 1,
    "lv": {
      "1": "長い追加のスタミナゲージを得る"
    }
  },
  {
    "id": 123,
    "name": "ウォークライⅠ",
    "kana": "うぉーくらい",
    "text": "ジェスチャー「雄叫び」をした時、一定時間、周囲の攻撃力が少し上昇。オトモとサポートハンターには効果が大きい。",
    "max": 1,
    "lv": {
      "1": "ジェスチャー「雄叫び」をした時、一定時間、周囲の攻撃力が少し上昇。オトモとサポートハンターには効果が大きい。"
    }
  },
  {
    "id": 124,
    "name": "ウォークライⅡ",
    "kana": "うぉーくらい",
    "text": "ジェスチャー「雄叫び」をした時、一定時間、周囲の攻撃力が上昇。オトモとサポートハンターには効果が大きい。",
    "max": 1,
    "lv": {
      "1": "ジェスチャー「雄叫び」をした時、一定時間、周囲の攻撃力が上昇。オトモとサポートハンターには効果が大きい。"
    }
  },
  {
    "id": 125,
    "name": "無傷の重装Ⅰ",
    "kana": "むきずのじゅうそう",
    "text": "体力が最大の時、受けるダメージを5%軽減する",
    "max": 1,
    "lv": {
      "1": "体力が最大の時、受けるダメージを5%軽減する"
    }
  },
  {
    "id": 126,
    "name": "無傷の重装Ⅱ",
    "kana": "むきずのじゅうそう",
    "text": "体力が最大の時、受けるダメージを10%軽減する",
    "max": 1,
    "lv": {
      "1": "体力が最大の時、受けるダメージを10%軽減する"
    }
  },
  {
    "id": 139,
    "name": "束縛反攻Ⅰ",
    "kana": "そくばくはんこう",
    "text": "糸拘束状態、凍結状態の回復時、または拘束攻撃から解放された時、鍔迫り合いの後、一定時間、攻撃力が上昇",
    "max": 1,
    "lv": {
      "1": "糸拘束状態、凍結状態の回復時、または拘束攻撃から解放された時、鍔迫り合いの後、一定時間、攻撃力が上昇"
    }
  },
  {
    "id": 140,
    "name": "束縛反攻Ⅱ",
    "kana": "そくばくはんこう",
    "text": "糸拘束状態、凍結状態の回復時、または拘束攻撃から解放された時、鍔迫り合いの後、一定時間、攻撃力が大きく上昇",
    "max": 1,
    "lv": {
      "1": "糸拘束状態、凍結状態の回復時、または拘束攻撃から解放された時、鍔迫り合いの後、一定時間、攻撃力が大きく上昇"
    }
  },
  {
    "id": 141,
    "name": "黒蝕一体Ⅰ",
    "kana": "こくしょくいったい",
    "text": "大型モンスターと対峙した時、狂竜症に感染する。",
    "max": 1,
    "lv": {
      "1": "大型モンスターと対峙した時、狂竜症に感染する。"
    }
  },
  {
    "id": 142,
    "name": "黒蝕一体Ⅱ",
    "kana": "こくしょくいったい",
    "text": "大型モンスターと対峙した時、狂竜症に感染し、攻撃力が上昇する。克服時、さらに攻撃力が上昇する。",
    "max": 1,
    "lv": {
      "1": "大型モンスターと対峙した時、狂竜症に感染し、攻撃力が上昇する。克服時、さらに攻撃力が上昇する。"
    }
  },
  {
    "id": 156,
    "name": "恨撃Ⅰ",
    "kana": "こんげきいち",
    "text": "「逆恨み」スキル発動中、追加で少しダメージを与える",
    "max": 1,
    "lv": {
      "1": "「逆恨み」スキル発動中、追加で少しダメージを与える"
    }
  },
  {
    "id": 157,
    "name": "恨撃Ⅱ",
    "kana": "こんげきに",
    "text": "「逆恨み」スキル発動中、追加でダメージを与える",
    "max": 1,
    "lv": {
      "1": "「逆恨み」スキル発動中、追加でダメージを与える"
    }
  },
  {
    "id": 158,
    "name": "加速再生Ⅰ",
    "kana": "かそくさいせいいち",
    "text": "継続してモンスターに攻撃を当てると、体力が少し回復する(武器種により回復力は変動)",
    "max": 1,
    "lv": {
      "1": "継続してモンスターに攻撃を当てると、体力が少し回復する(武器種により回復力は変動)"
    }
  },
  {
    "id": 159,
    "name": "加速再生Ⅱ",
    "kana": "かそくさいせいに",
    "text": "継続してモンスターに攻撃を当てると、体力が回復する(武器種により回復力は変動)",
    "max": 1,
    "lv": {
      "1": "継続してモンスターに攻撃を当てると、体力が回復する(武器種により回復力は変動)"
    }
  },
  {
    "id": 161,
    "name": "蛮勇の食卓Ⅰ",
    "kana": "ばんゆうのしょくたく",
    "text": "こんがり肉などのアイテムを食べた時、一定時間、基礎攻撃力+15",
    "max": 1,
    "lv": {
      "1": "こんがり肉などのアイテムを食べた時、一定時間、基礎攻撃力+15"
    }
  },
  {
    "id": 162,
    "name": "蛮勇の食卓Ⅱ",
    "kana": "ばんゆうのしょくたく",
    "text": "こんがり肉などのアイテムを食べた時、一定時間、基礎攻撃力+25",
    "max": 1,
    "lv": {
      "1": "こんがり肉などのアイテムを食べた時、一定時間、基礎攻撃力+25"
    }
  },
  {
    "id": 164,
    "name": "泡沫の舞Ⅰ",
    "kana": "うたかたのまい",
    "text": "泡状態【大】にならなくなる。泡状態時に回避能力を強化する。",
    "max": 1,
    "lv": {
      "1": "泡状態【大】にならなくなる。泡状態時に回避能力を強化する。"
    }
  },
  {
    "id": 165,
    "name": "泡沫の舞Ⅱ",
    "kana": "うたかたのまい",
    "text": "泡状態【大】にならなくなる。泡状態時に回避能力を強化する。さらに回避行動を複数回行うことで泡状態【小】になる。",
    "max": 1,
    "lv": {
      "1": "泡状態【大】にならなくなる。泡状態時に回避能力を強化する。さらに回避行動を複数回行うことで泡状態【小】になる。"
    }
  },
  {
    "id": 166,
    "name": "超回復力Ⅰ",
    "kana": "ちょうかいふくりょく",
    "text": "体力に赤ゲージが無い状態でも、最大値までゆるやかに自動回復が継続する。",
    "max": 1,
    "lv": {
      "1": "体力に赤ゲージが無い状態でも、最大値までゆるやかに自動回復が継続する。"
    }
  },
  {
    "id": 167,
    "name": "超回復力Ⅱ",
    "kana": "ちょうかいふくりょく",
    "text": "体力に赤ゲージが無い状態でも、最大値まで自動回復が継続する。",
    "max": 1,
    "lv": {
      "1": "体力に赤ゲージが無い状態でも、最大値まで自動回復が継続する。"
    }
  }
]